barrett/__init__.py
barrett/data.py
barrett/posterior.py
barrett/profilelikelihood.py
barrett/util.py
barrett-0.2.1.dist-info/DESCRIPTION.rst
barrett-0.2.1.dist-info/METADATA
barrett-0.2.1.dist-info/RECORD
barrett-0.2.1.dist-info/WHEEL
barrett-0.2.1.dist-info/metadata.json
barrett-0.2.1.dist-info/top_level.txt
