Metadata-Version: 2.0
Name: barrett
Version: 0.2.1
Summary: out-of-core processing and plotting of MultiNest output
Home-page: https://github.com/sliem/barrett
Author: Sebastian Liem
Author-email: sebastian@liem.se
License: ISC
Keywords: out-of-core multinest statistics visualisation
Platform: UNKNOWN
Classifier: Development Status :: 4 - Beta
Classifier: Intended Audience :: Science/Research
Classifier: Topic :: Scientific/Engineering :: Visualization
Classifier: License :: OSI Approved :: ISC License (ISCL)
Classifier: Programming Language :: Python :: 3
Requires-Dist: h5py
Requires-Dist: matplotlib
Requires-Dist: numpy
Requires-Dist: scipy
